matdb/__init__.py
matdb/_version.py
matdb/core.py
matdb/utils.py
matdb-0.0.11.dist-info/LICENSE
matdb-0.0.11.dist-info/METADATA
matdb-0.0.11.dist-info/WHEEL
matdb-0.0.11.dist-info/top_level.txt
matdb-0.0.11.dist-info/RECORD
