Metadata-Version: 2.1
Name: matdb
Version: 0.0.11
Summary: Welcome to MatDB, a material science database designed to be light weight and portable.
Author-email: Logan Lang <lllang@mix.wvu.edu>
License: MIT License
Project-URL: Repository, https://github.com/romerogroup/MatDB
Project-URL: Issues, https://github.com/romerogroup/MathDB/issues
Project-URL: Changelog, https://github.com/romerogroup/MatDB/CHANGELOG.md
Keywords: materials,science,database,python
Classifier: Programming Language :: Python :: 3
Requires-Python: >=3.8
License-File: LICENSE
Requires-Dist: python-dotenv
Requires-Dist: parquetdb
Requires-Dist: pymatgen
Provides-Extra: dev
Requires-Dist: sphinx ; extra == 'dev'
Requires-Dist: sphinx-rtd-theme ; extra == 'dev'
Provides-Extra: materials
Requires-Dist: ase ; extra == 'materials'
Requires-Dist: mendeleev ; extra == 'materials'
Requires-Dist: matminer ; extra == 'materials'
Requires-Dist: coxeter ; extra == 'materials'
Requires-Dist: crystals ; extra == 'materials'
